geoip/__init__.py
geoip/__main__.py
geoip/lookup.py
Surfy.GeoIP-1.0.2.dist-info/LICENSE.TXT
Surfy.GeoIP-1.0.2.dist-info/METADATA
Surfy.GeoIP-1.0.2.dist-info/WHEEL
Surfy.GeoIP-1.0.2.dist-info/top_level.txt
Surfy.GeoIP-1.0.2.dist-info/RECORD
