Metadata-Version: 2.1
Name: Surfy.GeoIP
Version: 1.0.2
Summary: Best Free Rest API for IP-based user location detection
Author: Alexander Yermolenko
Project-URL: Homepage, https://surfy.one/geoip
Project-URL: GitHub, https://github.com/hqdaemon/geoip.py
Project-URL: Bug Tracker, https://github.com/hqdaemon/geoip.py/issues
Classifier: Programming Language :: Python :: 3
Classifier: License :: OSI Approved :: MIT License
Classifier: Operating System :: OS Independent
Requires-Python: >=3.7
License-File: LICENSE.TXT
